{
  "course_name": "CSS",
  "description": "CSS is the language we use to style an HTML document. CSS describes how HTML elements should be displayed. This tutorial will teach you CSS from basic to advanced. Tip: Sign in to track your progress - it's free. This CSS tutorial contains hundreds of CSS examples. With our online editor, you can edit the CSS, and click on a button to view the result. Click on the \"Try it Yourself\" button to see how it works. Learn from over 300 examples! With our editor, you can edit the CSS, and click on a button to view the result. Go to CSS Examples! We recommend reading this tutorial, in the sequence listed in the menu. If you have a large screen, the menu will always be present on the left. If you have a small screen, open the menu by clicking the top menu sign ☰. We have created some responsive W3.CSS templates for you to use. You are free to modify, save, share, and use them in all your projects. Free CSS Templates!",
  "course_summary": [],
  "glossary": [
    "backend",
    "background attachment",
    "background clip",
    "background image",
    "background origin",
    "background repeat",
    "background shorthand",
    "background size",
    "border color",
    "border shorthand",
    "border sides",
    "border width",
    "box shadow",
    "clear",
    "conic gradients",
    "css accessibility",
    "css advanced",
    "css align",
    "css animatable",
    "css animations",
    "css at-rules",
    "css backgrounds",
    "css bootcamp",
    "css borders",
    "css buttons",
    "css colors",
    "css combinators",
    "css comments",
    "css counters",
    "css display",
    "css dropdowns",
    "css editor",
    "css errors",
    "css exercises",
    "css flexbox",
    "css float",
    "css fonts",
    "css forms",
    "css functions",
    "css gradients",
    "css grid",
    "css home",
    "css icons",
    "css important",
    "css inline-block",
    "css links",
    "css lists",
    "css margins",
    "css masking",
    "css max-width",
    "css object-fit",
    "css object-position",
    "css opacity",
    "css optimization",
    "css outline",
    "css overflow",
    "css padding",
    "css pagination",
    "css position",
    "css property",
    "css pseudo-classes",
    "css pseudo-elements",
    "css quiz",
    "css reference",
    "css references",
    "css responsive",
    "css sass",
    "css selectors",
    "css shadows",
    "css snippets",
    "css specificity",
    "css supports",
    "css syllabus",
    "css syntax",
    "css tables",
    "css templates",
    "css text",
    "css tooltips",
    "css transitions",
    "css units",
    "css variables",
    "css website",
    "css z-index",
    "exercises",
    "flex container",
    "flex items",
    "flex responsive",
    "flexbox intro",
    "font fallbacks",
    "font google",
    "font pairings",
    "font shorthand",
    "font size",
    "font style",
    "free",
    "grid container",
    "grid intro",
    "grid item",
    "grid lines",
    "hex",
    "horizontal navbar",
    "hsl",
    "javascript",
    "margin collapse",
    "note",
    "outline color",
    "outline offset",
    "outline shorthand",
    "outline width",
    "overriding variables",
    "programs",
    "radial gradients",
    "report error",
    "rgb",
    "rounded borders",
    "rwd frameworks",
    "rwd images",
    "rwd intro",
    "rwd templates",
    "rwd videos",
    "rwd viewport",
    "table alignment",
    "table responsive",
    "table size",
    "table styling",
    "text alignment",
    "text decoration",
    "text shadow",
    "text spacing",
    "text transformation",
    "vertical navbar",
    "w3.css",
    "w3schools spaces"
  ],
  "objectives": [
    "View your completed tutorials, exercises, and quizzes",
    "Keep an eye on your progress and daily streaks",
    "Set goals and create learning paths",
    "Create your own personal website"
  ]
}